README.md
pyproject.toml
setup.py
aleph/AstEph.py
aleph/DataBase.py
aleph/Query.py
aleph/__init__.py
aleph/aleph_utils.py
aleph/cutils.c
aleph/cutils.h
aleph/pycutils.py
astro_aleph.egg-info/PKG-INFO
astro_aleph.egg-info/SOURCES.txt
astro_aleph.egg-info/dependency_links.txt
astro_aleph.egg-info/requires.txt
astro_aleph.egg-info/top_level.txt