Metadata-Version: 2.1
Name: astro-aleph
Version: 0.1
Summary: ALeRCE's Ephemeris
Home-page: https://github.com/josepenaz/ephs
Author: Jose Pena Z.
Author-email: jpena@das.uchile.cl
License: UNKNOWN
Platform: UNKNOWN
Requires-Python: >=3.6
